{
  "week": 4,
  "period": "2026-01-19 — 2026-01-25",
  "totals": {
    "revenue": 126331.31,
    "expense": 113411.01,
    "gross_profit": 12920.31,
    "margin_pct": 10.23
  },
  "byType": {
    "CAINIAO": {
      "count": 7,
      "revenue": 97481.76,
      "expense": 93183.45,
      "gross_profit": 4298.33,
      "margin_pct": 4.41,
      "note": "Включает накладные расходы (ФОТ, E-Transit и пр.) — итог из TOTAL колонки PNL"
    },
    "MPO": {
      "count": 1,
      "revenue": 1509.98,
      "expense": 1103.81,
      "gross_profit": 406.17,
      "margin_pct": 26.9
    },
    "MKO": {
      "count": 4,
      "revenue": 27339.57,
      "expense": 19123.75,
      "gross_profit": 8215.81,
      "margin_pct": 30.05
    }
  },
  "umbrella_uzum_cb": {
    "revenue": 28849.55,
    "expense": 20227.56,
    "gross_profit": 8621.98,
    "margin_pct": 29.89
  },
  "parties": [
    {
      "col": "AL",
      "type": "CAINIAO",
      "num": "987",
      "date": "2026-01-19",
      "revenue": 14781.71,
      "expense": 13671.13,
      "gross_profit": 1110.58,
      "margin_pct": 7.51,
      "weight_net": 777.73,
      "weight_gross": 820.0,
      "weight_vol": 972.5,
      "marker1_tariff": null,
      "marker2_volnet": null,
      "marker3_grossnet": null,
      "total_kg": 820.0,
      "mix": []
    },
    {
      "col": "AM",
      "type": "CAINIAO",
      "num": "988",
      "date": "2026-01-20",
      "revenue": 13281.68,
      "expense": 12996.63,
      "gross_profit": 285.05,
      "margin_pct": 2.15,
      "weight_net": 829.15,
      "weight_gross": 868.0,
      "weight_vol": 1084.5,
      "marker1_tariff": null,
      "marker2_volnet": null,
      "marker3_grossnet": null,
      "total_kg": 868.0,
      "mix": []
    },
    {
      "col": "AN",
      "type": "CAINIAO",
      "num": "989",
      "date": "2026-01-23",
      "revenue": 14671.52,
      "expense": 14069.11,
      "gross_profit": 602.42,
      "margin_pct": 4.11,
      "weight_net": 779.17,
      "weight_gross": 803.0,
      "weight_vol": 1000.0,
      "marker1_tariff": null,
      "marker2_volnet": null,
      "marker3_grossnet": null,
      "total_kg": 803.0,
      "mix": []
    },
    {
      "col": "AO",
      "type": "CAINIAO",
      "num": "990",
      "date": "2026-01-23",
      "revenue": 12561.78,
      "expense": 12090.03,
      "gross_profit": 471.75,
      "margin_pct": 3.76,
      "weight_net": 672.63,
      "weight_gross": 699.0,
      "weight_vol": 893.0,
      "marker1_tariff": null,
      "marker2_volnet": null,
      "marker3_grossnet": null,
      "total_kg": 699.0,
      "mix": []
    },
    {
      "col": "AP",
      "type": "CAINIAO",
      "num": "991",
      "date": "2026-01-24",
      "revenue": 13290.67,
      "expense": 12490.27,
      "gross_profit": 800.4,
      "margin_pct": 6.02,
      "weight_net": 692.9,
      "weight_gross": 724.0,
      "weight_vol": 889.0,
      "marker1_tariff": null,
      "marker2_volnet": null,
      "marker3_grossnet": null,
      "total_kg": 724.0,
      "mix": []
    },
    {
      "col": "AQ",
      "type": "CAINIAO",
      "num": "992",
      "date": "2026-01-24",
      "revenue": 14605.13,
      "expense": 14311.18,
      "gross_profit": 293.96,
      "margin_pct": 2.01,
      "weight_net": 777.26,
      "weight_gross": 814.0,
      "weight_vol": 1018.0,
      "marker1_tariff": null,
      "marker2_volnet": null,
      "marker3_grossnet": null,
      "total_kg": 814.0,
      "mix": []
    },
    {
      "col": "AR",
      "type": "CAINIAO",
      "num": "993",
      "date": "2026-01-25",
      "revenue": 14289.27,
      "expense": 13555.1,
      "gross_profit": 734.17,
      "margin_pct": 5.14,
      "weight_net": 759.14,
      "weight_gross": 801.0,
      "weight_vol": 984.0,
      "marker1_tariff": null,
      "marker2_volnet": null,
      "marker3_grossnet": null,
      "total_kg": 801.0,
      "mix": []
    },
    {
      "col": "AS",
      "type": "MPO",
      "num": "988",
      "date": "2026-01-20",
      "revenue": 1509.98,
      "expense": 1103.81,
      "gross_profit": 406.17,
      "margin_pct": 26.9,
      "weight_net": null,
      "weight_gross": 868.0,
      "weight_vol": 1084.5,
      "marker1_tariff": 4.35,
      "marker2_volnet": null,
      "marker3_grossnet": null,
      "total_kg": 868.0,
      "mix": []
    },
    {
      "col": "AT",
      "type": "MKO",
      "num": "42",
      "date": "2026-01-19",
      "revenue": 5943.71,
      "expense": 4331.8,
      "gross_profit": 1611.91,
      "margin_pct": 27.12,
      "weight_net": 232.9,
      "weight_gross": 227.0,
      "weight_vol": 319.0,
      "marker1_tariff": 8.41,
      "marker2_volnet": null,
      "marker3_grossnet": null,
      "total_kg": 227.0,
      "mix": []
    },
    {
      "col": "AU",
      "type": "MKO",
      "num": "43",
      "date": "2026-01-19",
      "revenue": 6041.98,
      "expense": 5241.69,
      "gross_profit": 800.29,
      "margin_pct": 13.25,
      "weight_net": 438.2,
      "weight_gross": 460.0,
      "weight_vol": 600.0,
      "marker1_tariff": 4.22,
      "marker2_volnet": null,
      "marker3_grossnet": null,
      "total_kg": 460.0,
      "mix": []
    },
    {
      "col": "AV",
      "type": "MKO",
      "num": "44",
      "date": "2026-01-22",
      "revenue": 6982.3,
      "expense": 5047.68,
      "gross_profit": 1934.61,
      "margin_pct": 27.71,
      "weight_net": 495.55,
      "weight_gross": 518.0,
      "weight_vol": 713.0,
      "marker1_tariff": 3.69,
      "marker2_volnet": null,
      "marker3_grossnet": null,
      "total_kg": 518.0,
      "mix": []
    },
    {
      "col": "AW",
      "type": "MKO",
      "num": "45",
      "date": "2026-01-25",
      "revenue": 8371.58,
      "expense": 4502.58,
      "gross_profit": 3869.0,
      "margin_pct": 46.22,
      "weight_net": 609.2,
      "weight_gross": 634.0,
      "weight_vol": 857.0,
      "marker1_tariff": 3.69,
      "marker2_volnet": null,
      "marker3_grossnet": null,
      "total_kg": 634.0,
      "mix": []
    }
  ]
}