{
  "week": 17,
  "year": 2025,
  "period": "W17 2025",
  "totals": {
    "revenue": 142619.73,
    "expense": 103663.43,
    "gross_profit": 38956.3,
    "margin_pct": 27.31
  },
  "byType": {
    "CAINIAO": {
      "count": 12,
      "revenue": 142619.73,
      "expense": 103663.43,
      "gross_profit": 38956.3,
      "margin_pct": 27.31
    },
    "MPO": {
      "count": 0,
      "revenue": 0,
      "expense": 0,
      "gross_profit": 0,
      "margin_pct": 0
    },
    "MKO": {
      "count": 0,
      "revenue": 0,
      "expense": 0,
      "gross_profit": 0,
      "margin_pct": 0
    }
  },
  "umbrella_uzum_cb": {
    "revenue": 0,
    "expense": 0,
    "gross_profit": 0,
    "margin_pct": 0
  },
  "parties": [
    {
      "col": "167",
      "type": "CAINIAO",
      "num": "672",
      "date": "2025-04-21T00:00:00",
      "revenue": 17403.55,
      "expense": 13290.97,
      "gross_profit": 4112.58,
      "margin_pct": 23.63,
      "weight_net": null,
      "weight_gross": null,
      "weight_vol": null,
      "marker1_tariff": 3.8499999999999996,
      "marker2_volnet": 1.250554815801151,
      "marker3_grossnet": 1.0519307589880134,
      "total_kg": null,
      "total_pcs": 0,
      "mix": [
        {
          "country": "UZ",
          "subtype": "RM",
          "pcs": 0,
          "kg": 0.53
        },
        {
          "country": "UZ",
          "subtype": "SRM",
          "pcs": 0,
          "kg": 0.09
        },
        {
          "country": "UZ",
          "subtype": "SRMA",
          "pcs": 0,
          "kg": 0.07
        },
        {
          "country": "UZ",
          "subtype": "SRMB",
          "pcs": 0,
          "kg": 0.21
        },
        {
          "country": "UZ",
          "subtype": "SRMC",
          "pcs": 0,
          "kg": 0.1
        },
        {
          "country": "BY",
          "subtype": "RRM",
          "pcs": 0,
          "kg": 0.6
        },
        {
          "country": "BY",
          "subtype": "SRM",
          "pcs": 0,
          "kg": 0.17
        },
        {
          "country": "BY",
          "subtype": "NRM",
          "pcs": 0,
          "kg": 0.23
        },
        {
          "country": "KG",
          "subtype": "RM",
          "pcs": 0,
          "kg": 0.64
        },
        {
          "country": "KG",
          "subtype": "NRM",
          "pcs": 0,
          "kg": 0.36
        },
        {
          "country": "AZ",
          "subtype": "RM",
          "pcs": 0,
          "kg": 0.63
        },
        {
          "country": "AZ",
          "subtype": "NRM",
          "pcs": 0,
          "kg": 0.37
        }
      ]
    },
    {
      "col": "168",
      "type": "CAINIAO",
      "num": "673",
      "date": "2025-04-23T00:00:00",
      "revenue": 15356.5,
      "expense": 11588.98,
      "gross_profit": 3767.51,
      "margin_pct": 24.53,
      "weight_net": null,
      "weight_gross": null,
      "weight_vol": null,
      "marker1_tariff": 3.5000000000000004,
      "marker2_volnet": 1.307863529470943,
      "marker3_grossnet": 1.0400030181466056,
      "total_kg": null,
      "total_pcs": 0,
      "mix": [
        {
          "country": "UZ",
          "subtype": "RM",
          "pcs": 0,
          "kg": 0.7
        },
        {
          "country": "UZ",
          "subtype": "SRM",
          "pcs": 0,
          "kg": 0.04
        },
        {
          "country": "UZ",
          "subtype": "SRMA",
          "pcs": 0,
          "kg": 0.04
        },
        {
          "country": "UZ",
          "subtype": "SRMB",
          "pcs": 0,
          "kg": 0.15
        },
        {
          "country": "UZ",
          "subtype": "SRMC",
          "pcs": 0,
          "kg": 0.06
        },
        {
          "country": "BY",
          "subtype": "RRM",
          "pcs": 0,
          "kg": 0.75
        },
        {
          "country": "BY",
          "subtype": "SRM",
          "pcs": 0,
          "kg": 0.15
        },
        {
          "country": "BY",
          "subtype": "NRM",
          "pcs": 0,
          "kg": 0.09
        },
        {
          "country": "KG",
          "subtype": "RM",
          "pcs": 0,
          "kg": 0.78
        },
        {
          "country": "KG",
          "subtype": "NRM",
          "pcs": 0,
          "kg": 0.22
        },
        {
          "country": "AZ",
          "subtype": "RM",
          "pcs": 0,
          "kg": 0.78
        },
        {
          "country": "AZ",
          "subtype": "NRM",
          "pcs": 0,
          "kg": 0.22
        }
      ]
    },
    {
      "col": "169",
      "type": "CAINIAO",
      "num": "674",
      "date": "2025-04-23T00:00:00",
      "revenue": 22263.32,
      "expense": 17108.55,
      "gross_profit": 5154.78,
      "margin_pct": 23.15,
      "weight_net": null,
      "weight_gross": null,
      "weight_vol": null,
      "marker1_tariff": 3.6999999999999997,
      "marker2_volnet": 1.3024238592966542,
      "marker3_grossnet": 1.0261783731825367,
      "total_kg": null,
      "total_pcs": 0,
      "mix": [
        {
          "country": "UZ",
          "subtype": "RM",
          "pcs": 0,
          "kg": 0.58
        },
        {
          "country": "UZ",
          "subtype": "SRM",
          "pcs": 0,
          "kg": 0.06
        },
        {
          "country": "UZ",
          "subtype": "SRMA",
          "pcs": 0,
          "kg": 0.06
        },
        {
          "country": "UZ",
          "subtype": "SRMB",
          "pcs": 0,
          "kg": 0.2
        },
        {
          "country": "UZ",
          "subtype": "SRMC",
          "pcs": 0,
          "kg": 0.1
        },
        {
          "country": "BY",
          "subtype": "RRM",
          "pcs": 0,
          "kg": 0.63
        },
        {
          "country": "BY",
          "subtype": "SRM",
          "pcs": 0,
          "kg": 0.2
        },
        {
          "country": "BY",
          "subtype": "NRM",
          "pcs": 0,
          "kg": 0.17
        },
        {
          "country": "KG",
          "subtype": "RM",
          "pcs": 0,
          "kg": 0.7
        },
        {
          "country": "KG",
          "subtype": "NRM",
          "pcs": 0,
          "kg": 0.3
        },
        {
          "country": "AZ",
          "subtype": "RM",
          "pcs": 0,
          "kg": 0.66
        },
        {
          "country": "AZ",
          "subtype": "NRM",
          "pcs": 0,
          "kg": 0.34
        }
      ]
    },
    {
      "col": "170",
      "type": "CAINIAO",
      "num": "675",
      "date": "2025-04-25T00:00:00",
      "revenue": 35082.5,
      "expense": 26246.51,
      "gross_profit": 8835.99,
      "margin_pct": 25.19,
      "weight_net": null,
      "weight_gross": null,
      "weight_vol": null,
      "marker1_tariff": 3.8499999999999996,
      "marker2_volnet": 1.2041207688534041,
      "marker3_grossnet": 1.0251750434821343,
      "total_kg": null,
      "total_pcs": 0,
      "mix": [
        {
          "country": "UZ",
          "subtype": "RM",
          "pcs": 0,
          "kg": 0.53
        },
        {
          "country": "UZ",
          "subtype": "SRM",
          "pcs": 0,
          "kg": 0.06
        },
        {
          "country": "UZ",
          "subtype": "SRMA",
          "pcs": 0,
          "kg": 0.07
        },
        {
          "country": "UZ",
          "subtype": "SRMB",
          "pcs": 0,
          "kg": 0.23
        },
        {
          "country": "UZ",
          "subtype": "SRMC",
          "pcs": 0,
          "kg": 0.11
        },
        {
          "country": "BY",
          "subtype": "RRM",
          "pcs": 0,
          "kg": 0.64
        },
        {
          "country": "BY",
          "subtype": "SRM",
          "pcs": 0,
          "kg": 0.19
        },
        {
          "country": "BY",
          "subtype": "NRM",
          "pcs": 0,
          "kg": 0.17
        },
        {
          "country": "KG",
          "subtype": "RM",
          "pcs": 0,
          "kg": 0.74
        },
        {
          "country": "KG",
          "subtype": "NRM",
          "pcs": 0,
          "kg": 0.26
        },
        {
          "country": "AZ",
          "subtype": "RM",
          "pcs": 0,
          "kg": 0.7
        },
        {
          "country": "AZ",
          "subtype": "NRM",
          "pcs": 0,
          "kg": 0.3
        }
      ]
    },
    {
      "col": "171",
      "type": "CAINIAO",
      "num": "676",
      "date": "2025-04-25T00:00:00",
      "revenue": 19335.32,
      "expense": 14716.95,
      "gross_profit": 4618.37,
      "margin_pct": 23.89,
      "weight_net": null,
      "weight_gross": null,
      "weight_vol": null,
      "marker1_tariff": 3.5,
      "marker2_volnet": 1.3392991201465416,
      "marker3_grossnet": 1.0289981281843383,
      "total_kg": null,
      "total_pcs": 0,
      "mix": [
        {
          "country": "UZ",
          "subtype": "RM",
          "pcs": 0,
          "kg": 0.63
        },
        {
          "country": "UZ",
          "subtype": "SRM",
          "pcs": 0,
          "kg": 0.05
        },
        {
          "country": "UZ",
          "subtype": "SRMA",
          "pcs": 0,
          "kg": 0.06
        },
        {
          "country": "UZ",
          "subtype": "SRMB",
          "pcs": 0,
          "kg": 0.19
        },
        {
          "country": "UZ",
          "subtype": "SRMC",
          "pcs": 0,
          "kg": 0.08
        },
        {
          "country": "BY",
          "subtype": "RRM",
          "pcs": 0,
          "kg": 0.69
        },
        {
          "country": "BY",
          "subtype": "SRM",
          "pcs": 0,
          "kg": 0.17
        },
        {
          "country": "BY",
          "subtype": "NRM",
          "pcs": 0,
          "kg": 0.14
        },
        {
          "country": "KG",
          "subtype": "RM",
          "pcs": 0,
          "kg": 0.71
        },
        {
          "country": "KG",
          "subtype": "NRM",
          "pcs": 0,
          "kg": 0.29
        },
        {
          "country": "AZ",
          "subtype": "RM",
          "pcs": 0,
          "kg": 0.74
        },
        {
          "country": "AZ",
          "subtype": "NRM",
          "pcs": 0,
          "kg": 0.26
        }
      ]
    },
    {
      "col": "172",
      "type": "CAINIAO",
      "num": "677",
      "date": "2025-04-27T00:00:00",
      "revenue": 16986.4,
      "expense": 13166.31,
      "gross_profit": 3820.09,
      "margin_pct": 22.49,
      "weight_net": null,
      "weight_gross": null,
      "weight_vol": null,
      "marker1_tariff": 3.7,
      "marker2_volnet": 1.3782214407995148,
      "marker3_grossnet": 1.0294730023596879,
      "total_kg": null,
      "total_pcs": 0,
      "mix": [
        {
          "country": "UZ",
          "subtype": "RM",
          "pcs": 0,
          "kg": 0.52
        },
        {
          "country": "UZ",
          "subtype": "SRM",
          "pcs": 0,
          "kg": 0.09
        },
        {
          "country": "UZ",
          "subtype": "SRMA",
          "pcs": 0,
          "kg": 0.07
        },
        {
          "country": "UZ",
          "subtype": "SRMB",
          "pcs": 0,
          "kg": 0.22
        },
        {
          "country": "UZ",
          "subtype": "SRMC",
          "pcs": 0,
          "kg": 0.1
        },
        {
          "country": "BY",
          "subtype": "RRM",
          "pcs": 0,
          "kg": 0.63
        },
        {
          "country": "BY",
          "subtype": "SRM",
          "pcs": 0,
          "kg": 0.18
        },
        {
          "country": "BY",
          "subtype": "NRM",
          "pcs": 0,
          "kg": 0.2
        },
        {
          "country": "KG",
          "subtype": "RM",
          "pcs": 0,
          "kg": 0.66
        },
        {
          "country": "KG",
          "subtype": "NRM",
          "pcs": 0,
          "kg": 0.34
        },
        {
          "country": "AZ",
          "subtype": "RM",
          "pcs": 0,
          "kg": 0.68
        },
        {
          "country": "AZ",
          "subtype": "NRM",
          "pcs": 0,
          "kg": 0.32
        }
      ]
    },
    {
      "col": "173",
      "type": "CAINIAO",
      "num": "685",
      "date": "2025-04-21T00:00:00",
      "revenue": 634.84,
      "expense": 548.48,
      "gross_profit": 86.37,
      "margin_pct": 13.6,
      "weight_net": null,
      "weight_gross": null,
      "weight_vol": null,
      "marker1_tariff": 0.0,
      "marker2_volnet": 1.5293493635077793,
      "marker3_grossnet": 1.5293493635077793,
      "total_kg": null,
      "total_pcs": 1,
      "mix": [
        {
          "country": "BY",
          "subtype": "SRMDG",
          "pcs": 1,
          "kg": 1.0
        }
      ]
    },
    {
      "col": "174",
      "type": "CAINIAO",
      "num": "148",
      "date": "2025-04-21T00:00:00",
      "revenue": 3488.43,
      "expense": 2912.88,
      "gross_profit": 575.55,
      "margin_pct": 16.5,
      "weight_net": null,
      "weight_gross": null,
      "weight_vol": null,
      "marker1_tariff": 2.53,
      "marker2_volnet": null,
      "marker3_grossnet": null,
      "total_kg": null,
      "total_pcs": 0
    },
    {
      "col": "175",
      "type": "CAINIAO",
      "num": "87 YANDEX FARFETCH",
      "date": "2025-04-25T00:00:00",
      "revenue": 5341.78,
      "expense": 0.0,
      "gross_profit": 5341.78,
      "margin_pct": 100.0,
      "weight_net": null,
      "weight_gross": null,
      "weight_vol": null,
      "marker1_tariff": null,
      "marker2_volnet": null,
      "marker3_grossnet": null,
      "total_kg": null,
      "total_pcs": 0
    },
    {
      "col": "176",
      "type": "CAINIAO",
      "num": "88 YANDEX FARFETCH",
      "date": "2025-04-26T00:00:00",
      "revenue": 3172.92,
      "expense": 1771.18,
      "gross_profit": 1401.74,
      "margin_pct": 44.18,
      "weight_net": null,
      "weight_gross": null,
      "weight_vol": null,
      "marker1_tariff": null,
      "marker2_volnet": null,
      "marker3_grossnet": null,
      "total_kg": null,
      "total_pcs": 0
    },
    {
      "col": "177",
      "type": "CAINIAO",
      "num": "89 YANDEX FARFETCH",
      "date": "2025-04-27T00:00:00",
      "revenue": 1786.91,
      "expense": 1193.84,
      "gross_profit": 593.07,
      "margin_pct": 33.19,
      "weight_net": null,
      "weight_gross": null,
      "weight_vol": null,
      "marker1_tariff": null,
      "marker2_volnet": null,
      "marker3_grossnet": null,
      "total_kg": null,
      "total_pcs": 0
    },
    {
      "col": "178",
      "type": "CAINIAO",
      "num": "90 YANDEX FARFETCH",
      "date": "2025-04-25T00:00:00",
      "revenue": 1767.26,
      "expense": 1118.78,
      "gross_profit": 648.48,
      "margin_pct": 36.69,
      "weight_net": null,
      "weight_gross": null,
      "weight_vol": null,
      "marker1_tariff": null,
      "marker2_volnet": null,
      "marker3_grossnet": null,
      "total_kg": null,
      "total_pcs": 0
    }
  ]
}