{
  "week": 14,
  "year": 2025,
  "period": "W14 2025",
  "totals": {
    "revenue": 114937.64,
    "expense": 94230.76,
    "gross_profit": 20706.88,
    "margin_pct": 18.02
  },
  "byType": {
    "CAINIAO": {
      "count": 11,
      "revenue": 114937.64,
      "expense": 94230.76,
      "gross_profit": 20706.88,
      "margin_pct": 18.02
    },
    "MPO": {
      "count": 0,
      "revenue": 0,
      "expense": 0,
      "gross_profit": 0,
      "margin_pct": 0
    },
    "MKO": {
      "count": 0,
      "revenue": 0,
      "expense": 0,
      "gross_profit": 0,
      "margin_pct": 0
    }
  },
  "umbrella_uzum_cb": {
    "revenue": 0,
    "expense": 0,
    "gross_profit": 0,
    "margin_pct": 0
  },
  "parties": [
    {
      "col": "129",
      "type": "CAINIAO",
      "num": "652",
      "date": "2025-03-31T00:00:00",
      "revenue": 20983.72,
      "expense": 17029.56,
      "gross_profit": 3954.17,
      "margin_pct": 18.84,
      "weight_net": null,
      "weight_gross": null,
      "weight_vol": null,
      "marker1_tariff": 4.0,
      "marker2_volnet": 1.4021271114709433,
      "marker3_grossnet": 1.0350347771685113,
      "total_kg": null,
      "total_pcs": 0,
      "mix": [
        {
          "country": "UZ",
          "subtype": "RM",
          "pcs": 0,
          "kg": 0.54
        },
        {
          "country": "UZ",
          "subtype": "SRM",
          "pcs": 0,
          "kg": 0.08
        },
        {
          "country": "UZ",
          "subtype": "SRMA",
          "pcs": 0,
          "kg": 0.07
        },
        {
          "country": "UZ",
          "subtype": "SRMB",
          "pcs": 0,
          "kg": 0.21
        },
        {
          "country": "UZ",
          "subtype": "SRMC",
          "pcs": 0,
          "kg": 0.1
        },
        {
          "country": "BY",
          "subtype": "RRM",
          "pcs": 0,
          "kg": 0.64
        },
        {
          "country": "BY",
          "subtype": "SRM",
          "pcs": 0,
          "kg": 0.19
        },
        {
          "country": "BY",
          "subtype": "NRM",
          "pcs": 0,
          "kg": 0.18
        },
        {
          "country": "KG",
          "subtype": "RM",
          "pcs": 0,
          "kg": 0.66
        },
        {
          "country": "KG",
          "subtype": "NRM",
          "pcs": 0,
          "kg": 0.34
        },
        {
          "country": "AZ",
          "subtype": "RM",
          "pcs": 0,
          "kg": 0.76
        },
        {
          "country": "AZ",
          "subtype": "NRM",
          "pcs": 0,
          "kg": 0.24
        }
      ]
    },
    {
      "col": "130",
      "type": "CAINIAO",
      "num": "653",
      "date": "2025-04-02T00:00:00",
      "revenue": 19779.81,
      "expense": 17742.08,
      "gross_profit": 2037.72,
      "margin_pct": 10.3,
      "weight_net": null,
      "weight_gross": null,
      "weight_vol": null,
      "marker1_tariff": 4.0,
      "marker2_volnet": 1.5934237182483995,
      "marker3_grossnet": 1.1200716845878114,
      "total_kg": null,
      "total_pcs": 0,
      "mix": [
        {
          "country": "UZ",
          "subtype": "RM",
          "pcs": 0,
          "kg": 0.51
        },
        {
          "country": "UZ",
          "subtype": "SRM",
          "pcs": 0,
          "kg": 0.1
        },
        {
          "country": "UZ",
          "subtype": "SRMA",
          "pcs": 0,
          "kg": 0.06
        },
        {
          "country": "UZ",
          "subtype": "SRMB",
          "pcs": 0,
          "kg": 0.21
        },
        {
          "country": "UZ",
          "subtype": "SRMC",
          "pcs": 0,
          "kg": 0.11
        },
        {
          "country": "BY",
          "subtype": "RRM",
          "pcs": 0,
          "kg": 0.6
        },
        {
          "country": "BY",
          "subtype": "SRM",
          "pcs": 0,
          "kg": 0.18
        },
        {
          "country": "BY",
          "subtype": "NRM",
          "pcs": 0,
          "kg": 0.22
        },
        {
          "country": "KG",
          "subtype": "RM",
          "pcs": 0,
          "kg": 0.71
        },
        {
          "country": "KG",
          "subtype": "NRM",
          "pcs": 0,
          "kg": 0.29
        },
        {
          "country": "AZ",
          "subtype": "RM",
          "pcs": 0,
          "kg": 0.7
        },
        {
          "country": "AZ",
          "subtype": "NRM",
          "pcs": 0,
          "kg": 0.3
        }
      ]
    },
    {
      "col": "131",
      "type": "CAINIAO",
      "num": "654",
      "date": "2025-04-03T00:00:00",
      "revenue": 15537.32,
      "expense": 12256.87,
      "gross_profit": 3280.45,
      "margin_pct": 21.11,
      "weight_net": null,
      "weight_gross": null,
      "weight_vol": null,
      "marker1_tariff": 3.4999999999999996,
      "marker2_volnet": 1.4771048744460844,
      "marker3_grossnet": 1.0376661742983744,
      "total_kg": null,
      "total_pcs": 0,
      "mix": [
        {
          "country": "UZ",
          "subtype": "RM",
          "pcs": 0,
          "kg": 0.6
        },
        {
          "country": "UZ",
          "subtype": "SRM",
          "pcs": 0,
          "kg": 0.06
        },
        {
          "country": "UZ",
          "subtype": "SRMA",
          "pcs": 0,
          "kg": 0.07
        },
        {
          "country": "UZ",
          "subtype": "SRMB",
          "pcs": 0,
          "kg": 0.19
        },
        {
          "country": "UZ",
          "subtype": "SRMC",
          "pcs": 0,
          "kg": 0.09
        },
        {
          "country": "BY",
          "subtype": "RRM",
          "pcs": 0,
          "kg": 0.68
        },
        {
          "country": "BY",
          "subtype": "SRM",
          "pcs": 0,
          "kg": 0.14
        },
        {
          "country": "BY",
          "subtype": "NRM",
          "pcs": 0,
          "kg": 0.19
        },
        {
          "country": "KG",
          "subtype": "RM",
          "pcs": 0,
          "kg": 0.68
        },
        {
          "country": "KG",
          "subtype": "NRM",
          "pcs": 0,
          "kg": 0.32
        },
        {
          "country": "AZ",
          "subtype": "RM",
          "pcs": 0,
          "kg": 0.78
        },
        {
          "country": "AZ",
          "subtype": "NRM",
          "pcs": 0,
          "kg": 0.22
        }
      ]
    },
    {
      "col": "132",
      "type": "CAINIAO",
      "num": "655",
      "date": "2025-04-04T00:00:00",
      "revenue": 28457.08,
      "expense": 22667.87,
      "gross_profit": 5789.21,
      "margin_pct": 20.34,
      "weight_net": null,
      "weight_gross": null,
      "weight_vol": null,
      "marker1_tariff": 4.0,
      "marker2_volnet": 1.3916763310856228,
      "marker3_grossnet": 1.020840422502927,
      "total_kg": null,
      "total_pcs": 0,
      "mix": [
        {
          "country": "UZ",
          "subtype": "RM",
          "pcs": 0,
          "kg": 0.49
        },
        {
          "country": "UZ",
          "subtype": "SRM",
          "pcs": 0,
          "kg": 0.07
        },
        {
          "country": "UZ",
          "subtype": "SRMA",
          "pcs": 0,
          "kg": 0.08
        },
        {
          "country": "UZ",
          "subtype": "SRMB",
          "pcs": 0,
          "kg": 0.25
        },
        {
          "country": "UZ",
          "subtype": "SRMC",
          "pcs": 0,
          "kg": 0.11
        },
        {
          "country": "BY",
          "subtype": "RRM",
          "pcs": 0,
          "kg": 0.57
        },
        {
          "country": "BY",
          "subtype": "SRM",
          "pcs": 0,
          "kg": 0.2
        },
        {
          "country": "BY",
          "subtype": "NRM",
          "pcs": 0,
          "kg": 0.23
        },
        {
          "country": "KG",
          "subtype": "RM",
          "pcs": 0,
          "kg": 0.63
        },
        {
          "country": "KG",
          "subtype": "NRM",
          "pcs": 0,
          "kg": 0.37
        },
        {
          "country": "AZ",
          "subtype": "RM",
          "pcs": 0,
          "kg": 0.65
        },
        {
          "country": "AZ",
          "subtype": "NRM",
          "pcs": 0,
          "kg": 0.35
        }
      ]
    },
    {
      "col": "133",
      "type": "CAINIAO",
      "num": "656",
      "date": "2025-04-05T00:00:00",
      "revenue": 8935.28,
      "expense": 7232.51,
      "gross_profit": 1702.77,
      "margin_pct": 19.06,
      "weight_net": null,
      "weight_gross": null,
      "weight_vol": null,
      "marker1_tariff": 3.7999999999999994,
      "marker2_volnet": 1.4947025981448097,
      "marker3_grossnet": 1.0506880028135575,
      "total_kg": null,
      "total_pcs": 0,
      "mix": [
        {
          "country": "UZ",
          "subtype": "RM",
          "pcs": 0,
          "kg": 0.67
        },
        {
          "country": "UZ",
          "subtype": "SRM",
          "pcs": 0,
          "kg": 0.03
        },
        {
          "country": "UZ",
          "subtype": "SRMA",
          "pcs": 0,
          "kg": 0.06
        },
        {
          "country": "UZ",
          "subtype": "SRMB",
          "pcs": 0,
          "kg": 0.17
        },
        {
          "country": "UZ",
          "subtype": "SRMC",
          "pcs": 0,
          "kg": 0.07
        },
        {
          "country": "BY",
          "subtype": "RRM",
          "pcs": 0,
          "kg": 0.68
        },
        {
          "country": "BY",
          "subtype": "SRM",
          "pcs": 0,
          "kg": 0.17
        },
        {
          "country": "BY",
          "subtype": "NRM",
          "pcs": 0,
          "kg": 0.16
        },
        {
          "country": "KG",
          "subtype": "RM",
          "pcs": 0,
          "kg": 0.66
        },
        {
          "country": "KG",
          "subtype": "NRM",
          "pcs": 0,
          "kg": 0.34
        },
        {
          "country": "AZ",
          "subtype": "RM",
          "pcs": 0,
          "kg": 0.78
        },
        {
          "country": "AZ",
          "subtype": "NRM",
          "pcs": 0,
          "kg": 0.22
        }
      ]
    },
    {
      "col": "134",
      "type": "CAINIAO",
      "num": "657",
      "date": "2025-04-06T00:00:00",
      "revenue": 13227.81,
      "expense": 10751.69,
      "gross_profit": 2476.12,
      "margin_pct": 18.72,
      "weight_net": null,
      "weight_gross": null,
      "weight_vol": null,
      "marker1_tariff": 4.15,
      "marker2_volnet": 1.3988956475521133,
      "marker3_grossnet": 1.0261028760408641,
      "total_kg": null,
      "total_pcs": 0,
      "mix": [
        {
          "country": "UZ",
          "subtype": "RM",
          "pcs": 0,
          "kg": 0.56
        },
        {
          "country": "UZ",
          "subtype": "SRM",
          "pcs": 0,
          "kg": 0.08
        },
        {
          "country": "UZ",
          "subtype": "SRMA",
          "pcs": 0,
          "kg": 0.07
        },
        {
          "country": "UZ",
          "subtype": "SRMB",
          "pcs": 0,
          "kg": 0.22
        },
        {
          "country": "UZ",
          "subtype": "SRMC",
          "pcs": 0,
          "kg": 0.08
        },
        {
          "country": "BY",
          "subtype": "RRM",
          "pcs": 0,
          "kg": 0.58
        },
        {
          "country": "BY",
          "subtype": "SRM",
          "pcs": 0,
          "kg": 0.18
        },
        {
          "country": "BY",
          "subtype": "NRM",
          "pcs": 0,
          "kg": 0.24
        },
        {
          "country": "KG",
          "subtype": "RM",
          "pcs": 0,
          "kg": 0.63
        },
        {
          "country": "KG",
          "subtype": "NRM",
          "pcs": 0,
          "kg": 0.37
        },
        {
          "country": "AZ",
          "subtype": "RM",
          "pcs": 0,
          "kg": 0.71
        },
        {
          "country": "AZ",
          "subtype": "NRM",
          "pcs": 0,
          "kg": 0.29
        }
      ]
    },
    {
      "col": "135",
      "type": "CAINIAO",
      "num": "680",
      "date": "2025-04-01T00:00:00",
      "revenue": 545.34,
      "expense": 455.75,
      "gross_profit": 89.59,
      "margin_pct": 16.43,
      "weight_net": null,
      "weight_gross": null,
      "weight_vol": null,
      "marker1_tariff": 0.0,
      "marker2_volnet": 1.3935810810810811,
      "marker3_grossnet": 1.3935810810810811,
      "total_kg": null,
      "total_pcs": 1,
      "mix": [
        {
          "country": "BY",
          "subtype": "SRMDG",
          "pcs": 1,
          "kg": 1.0
        }
      ]
    },
    {
      "col": "136",
      "type": "CAINIAO",
      "num": "681",
      "date": "2025-04-01T00:00:00",
      "revenue": 745.68,
      "expense": 611.75,
      "gross_profit": 133.93,
      "margin_pct": 17.96,
      "weight_net": null,
      "weight_gross": null,
      "weight_vol": null,
      "marker1_tariff": 0.0,
      "marker2_volnet": 1.3950727218759276,
      "marker3_grossnet": 1.3950727218759276,
      "total_kg": null,
      "total_pcs": 1,
      "mix": [
        {
          "country": "BY",
          "subtype": "SRMDG",
          "pcs": 1,
          "kg": 1.0
        }
      ]
    },
    {
      "col": "137",
      "type": "CAINIAO",
      "num": "682",
      "date": "2025-04-01T00:00:00",
      "revenue": 807.06,
      "expense": 635.75,
      "gross_profit": 171.31,
      "margin_pct": 21.23,
      "weight_net": null,
      "weight_gross": null,
      "weight_vol": null,
      "marker1_tariff": 0.0,
      "marker2_volnet": 1.3004980630879912,
      "marker3_grossnet": 1.3004980630879912,
      "total_kg": null,
      "total_pcs": 1,
      "mix": [
        {
          "country": "BY",
          "subtype": "SRMDG",
          "pcs": 1,
          "kg": 1.0
        }
      ]
    },
    {
      "col": "138",
      "type": "CAINIAO",
      "num": "145",
      "date": "2025-03-31T00:00:00",
      "revenue": 2579.24,
      "expense": 2929.56,
      "gross_profit": -350.32,
      "margin_pct": -13.58,
      "weight_net": null,
      "weight_gross": null,
      "weight_vol": null,
      "marker1_tariff": 2.5299999999999994,
      "marker2_volnet": null,
      "marker3_grossnet": null,
      "total_kg": null,
      "total_pcs": 0
    },
    {
      "col": "139",
      "type": "CAINIAO",
      "num": "76 YANDEX FARFETCH",
      "date": "2025-04-04T00:00:00",
      "revenue": 3339.3,
      "expense": 1917.37,
      "gross_profit": 1421.93,
      "margin_pct": 42.58,
      "weight_net": null,
      "weight_gross": null,
      "weight_vol": null,
      "marker1_tariff": null,
      "marker2_volnet": null,
      "marker3_grossnet": null,
      "total_kg": null,
      "total_pcs": 0
    }
  ]
}