{
  "week": 16,
  "period": "2026-04-13 — 2026-04-19",
  "totals": {
    "revenue": 129365.12,
    "expense": 96074.38,
    "gross_profit": 33290.74,
    "margin_pct": 25.73
  },
  "byType": {
    "CAINIAO": {
      "count": 6,
      "revenue": 84614.48,
      "expense": 74478.6,
      "gross_profit": 10135.88,
      "margin_pct": 11.98,
      "note": "Marker 4 теперь хранится по партии: total_pcs = sum по странам (rows 23/32/41/50). UI суммирует партии."
    },
    "MPO": {
      "count": 6,
      "revenue": 1550.61,
      "expense": 936.07,
      "gross_profit": 614.54,
      "margin_pct": 39.63
    },
    "MKO": {
      "count": 9,
      "revenue": 43200.01,
      "expense": 20659.71,
      "gross_profit": 22540.3,
      "margin_pct": 52.18
    }
  },
  "umbrella_uzum_cb": {
    "revenue": 44750.62,
    "expense": 21595.78,
    "gross_profit": 23154.84,
    "margin_pct": 51.74
  },
  "parties": [
    {
      "col": "HH",
      "type": "CAINIAO",
      "num": "1071",
      "date": "2026-04-13",
      "revenue": 12189.08,
      "expense": 10518.24,
      "gross_profit": 1670.84,
      "margin_pct": 13.71,
      "weight_net": null,
      "weight_gross": null,
      "weight_vol": null,
      "marker1_tariff": 3.07,
      "marker2_volnet": 1.4143,
      "marker3_grossnet": 1.0615,
      "total_kg": 617.97,
      "total_pcs": 7063,
      "mix": [
        {
          "country": "UZ",
          "subtype": "RM",
          "pcs": 1752,
          "kg": 155.1
        },
        {
          "country": "BY",
          "subtype": "RRM",
          "pcs": 4422,
          "kg": 355.25
        },
        {
          "country": "KG",
          "subtype": "RM",
          "pcs": 113,
          "kg": 12.19
        },
        {
          "country": "AZ",
          "subtype": "RM",
          "pcs": 776,
          "kg": 95.43
        }
      ]
    },
    {
      "col": "HI",
      "type": "CAINIAO",
      "num": "1073",
      "date": "2026-04-14",
      "revenue": 15126.76,
      "expense": 12883.47,
      "gross_profit": 2243.29,
      "margin_pct": 14.83,
      "weight_net": null,
      "weight_gross": null,
      "weight_vol": null,
      "marker1_tariff": 3.21,
      "marker2_volnet": 1.3111,
      "marker3_grossnet": 1.0623,
      "total_kg": 771.9,
      "total_pcs": 9399,
      "mix": [
        {
          "country": "UZ",
          "subtype": "RM",
          "pcs": 2518,
          "kg": 204.1
        },
        {
          "country": "BY",
          "subtype": "RRM",
          "pcs": 5643,
          "kg": 427.72
        },
        {
          "country": "KG",
          "subtype": "RM",
          "pcs": 127,
          "kg": 13.36
        },
        {
          "country": "AZ",
          "subtype": "RM",
          "pcs": 1111,
          "kg": 126.72
        }
      ]
    },
    {
      "col": "HJ",
      "type": "CAINIAO",
      "num": "1074",
      "date": "2026-04-16",
      "revenue": 19954.42,
      "expense": 17151.4,
      "gross_profit": 2803.02,
      "margin_pct": 14.05,
      "weight_net": null,
      "weight_gross": null,
      "weight_vol": null,
      "marker1_tariff": 3.21,
      "marker2_volnet": 1.3597,
      "marker3_grossnet": 1.0684,
      "total_kg": 1012.69,
      "total_pcs": 10747,
      "mix": [
        {
          "country": "UZ",
          "subtype": "RM",
          "pcs": 2950,
          "kg": 259.7
        },
        {
          "country": "BY",
          "subtype": "RRM",
          "pcs": 6329,
          "kg": 577.73
        },
        {
          "country": "KG",
          "subtype": "RM",
          "pcs": 178,
          "kg": 19.66
        },
        {
          "country": "AZ",
          "subtype": "RM",
          "pcs": 1290,
          "kg": 155.6
        }
      ]
    },
    {
      "col": "HK",
      "type": "CAINIAO",
      "num": "1076",
      "date": "2026-04-17",
      "revenue": 11429.34,
      "expense": 10901.97,
      "gross_profit": 527.37,
      "margin_pct": 4.61,
      "weight_net": null,
      "weight_gross": null,
      "weight_vol": null,
      "marker1_tariff": 4.21,
      "marker2_volnet": 1.3637,
      "marker3_grossnet": 1.0847,
      "total_kg": 571.59,
      "total_pcs": 7310,
      "mix": [
        {
          "country": "UZ",
          "subtype": "RM",
          "pcs": 1658,
          "kg": 125.38
        },
        {
          "country": "BY",
          "subtype": "RRM",
          "pcs": 4931,
          "kg": 361.3
        },
        {
          "country": "KG",
          "subtype": "RM",
          "pcs": 84,
          "kg": 8.02
        },
        {
          "country": "AZ",
          "subtype": "RM",
          "pcs": 637,
          "kg": 76.89
        }
      ]
    },
    {
      "col": "HL",
      "type": "CAINIAO",
      "num": "1077",
      "date": "2026-04-18",
      "revenue": 20742.59,
      "expense": 17966.21,
      "gross_profit": 2776.39,
      "margin_pct": 13.38,
      "weight_net": null,
      "weight_gross": null,
      "weight_vol": null,
      "marker1_tariff": 3.21,
      "marker2_volnet": 1.3497,
      "marker3_grossnet": 1.0531,
      "total_kg": 1048.36,
      "total_pcs": 12203,
      "mix": [
        {
          "country": "UZ",
          "subtype": "RM",
          "pcs": 3081,
          "kg": 248.94
        },
        {
          "country": "BY",
          "subtype": "RRM",
          "pcs": 7572,
          "kg": 640.68
        },
        {
          "country": "KG",
          "subtype": "RM",
          "pcs": 174,
          "kg": 15.16
        },
        {
          "country": "AZ",
          "subtype": "RM",
          "pcs": 1376,
          "kg": 143.58
        }
      ]
    },
    {
      "col": "HM",
      "type": "CAINIAO",
      "num": "1078",
      "date": "2026-04-19",
      "revenue": 5172.29,
      "expense": 5057.31,
      "gross_profit": 114.98,
      "margin_pct": 2.22,
      "weight_net": null,
      "weight_gross": null,
      "weight_vol": null,
      "marker1_tariff": 4.37,
      "marker2_volnet": 1.3679,
      "marker3_grossnet": 1.1056,
      "total_kg": 266.83,
      "total_pcs": 3760,
      "mix": [
        {
          "country": "UZ",
          "subtype": "RM",
          "pcs": 793,
          "kg": 58.41
        },
        {
          "country": "BY",
          "subtype": "RRM",
          "pcs": 2648,
          "kg": 174.56
        },
        {
          "country": "KG",
          "subtype": "RM",
          "pcs": 41,
          "kg": 4.22
        },
        {
          "country": "AZ",
          "subtype": "RM",
          "pcs": 278,
          "kg": 29.64
        }
      ]
    },
    {
      "col": "HN",
      "type": "MPO",
      "num": "1071",
      "date": "2026-04-13",
      "revenue": 180.99,
      "expense": 103.96,
      "gross_profit": 77.03,
      "margin_pct": 42.56,
      "weight_net": null,
      "weight_gross": null,
      "weight_vol": null,
      "marker1_tariff": 3.07,
      "marker2_volnet": null,
      "marker3_grossnet": null,
      "total_kg": 12.05,
      "total_pcs": 39,
      "mix": [
        {
          "country": "UZ",
          "subtype": "MPO",
          "pcs": 39,
          "kg": 12.05
        }
      ],
      "mpo_num": null,
      "is_auto": false
    },
    {
      "col": "HO",
      "type": "MPO",
      "num": "1073",
      "date": "2026-04-14",
      "revenue": 327.91,
      "expense": 180.82,
      "gross_profit": 147.09,
      "margin_pct": 44.86,
      "weight_net": null,
      "weight_gross": null,
      "weight_vol": null,
      "marker1_tariff": 3.21,
      "marker2_volnet": null,
      "marker3_grossnet": null,
      "total_kg": 20.75,
      "total_pcs": 77,
      "mix": [
        {
          "country": "UZ",
          "subtype": "MPO",
          "pcs": 77,
          "kg": 20.75
        }
      ],
      "mpo_num": null,
      "is_auto": false
    },
    {
      "col": "HP",
      "type": "MPO",
      "num": "1074",
      "date": "2026-04-16",
      "revenue": 318.76,
      "expense": 184.44,
      "gross_profit": 134.32,
      "margin_pct": 42.14,
      "weight_net": null,
      "weight_gross": null,
      "weight_vol": null,
      "marker1_tariff": 3.21,
      "marker2_volnet": null,
      "marker3_grossnet": null,
      "total_kg": 21.85,
      "total_pcs": 65,
      "mix": [
        {
          "country": "UZ",
          "subtype": "MPO",
          "pcs": 65,
          "kg": 21.85
        }
      ],
      "mpo_num": null,
      "is_auto": false
    },
    {
      "col": "HQ",
      "type": "MPO",
      "num": "1076",
      "date": "2026-04-17",
      "revenue": 239.1,
      "expense": 163.35,
      "gross_profit": 75.74,
      "margin_pct": 31.68,
      "weight_net": null,
      "weight_gross": null,
      "weight_vol": null,
      "marker1_tariff": 4.21,
      "marker2_volnet": null,
      "marker3_grossnet": null,
      "total_kg": 17.2,
      "total_pcs": 44,
      "mix": [
        {
          "country": "UZ",
          "subtype": "MPO",
          "pcs": 44,
          "kg": 17.2
        }
      ],
      "mpo_num": null,
      "is_auto": false
    },
    {
      "col": "HR",
      "type": "MPO",
      "num": "1077",
      "date": "2026-04-18",
      "revenue": 216.7,
      "expense": 129.06,
      "gross_profit": 87.64,
      "margin_pct": 40.44,
      "weight_net": null,
      "weight_gross": null,
      "weight_vol": null,
      "marker1_tariff": 3.21,
      "marker2_volnet": null,
      "marker3_grossnet": null,
      "total_kg": 16.25,
      "total_pcs": 36,
      "mix": [
        {
          "country": "UZ",
          "subtype": "MPO",
          "pcs": 36,
          "kg": 16.25
        }
      ],
      "mpo_num": null,
      "is_auto": false
    },
    {
      "col": "HS",
      "type": "MPO",
      "num": "1078",
      "date": "2026-04-19",
      "revenue": 267.15,
      "expense": 174.44,
      "gross_profit": 92.71,
      "margin_pct": 34.7,
      "weight_net": null,
      "weight_gross": null,
      "weight_vol": null,
      "marker1_tariff": 4.37,
      "marker2_volnet": null,
      "marker3_grossnet": null,
      "total_kg": 17.2,
      "total_pcs": 61,
      "mix": [
        {
          "country": "UZ",
          "subtype": "MPO",
          "pcs": 61,
          "kg": 17.2
        }
      ],
      "mpo_num": null,
      "is_auto": false
    },
    {
      "col": "HT",
      "type": "MKO",
      "num": "98",
      "date": "2026-04-13",
      "revenue": 5103.49,
      "expense": 1903.0,
      "gross_profit": 3200.49,
      "margin_pct": 62.71,
      "weight_net": null,
      "weight_gross": null,
      "weight_vol": null,
      "marker1_tariff": 3.24,
      "marker2_volnet": 1.1795,
      "marker3_grossnet": 1.0003,
      "total_kg": 306.9,
      "total_pcs": 933,
      "mix": [
        {
          "country": "UZ",
          "subtype": "MKO",
          "pcs": 933,
          "kg": 306.9
        }
      ],
      "is_auto": true
    },
    {
      "col": "HU",
      "type": "MKO",
      "num": "99",
      "date": "2026-04-14",
      "revenue": 4265.43,
      "expense": 1668.38,
      "gross_profit": 2597.06,
      "margin_pct": 60.89,
      "weight_net": null,
      "weight_gross": null,
      "weight_vol": null,
      "marker1_tariff": 3.54,
      "marker2_volnet": 1.2425,
      "marker3_grossnet": 0.9988,
      "total_kg": 250.3,
      "total_pcs": 823,
      "mix": [
        {
          "country": "UZ",
          "subtype": "MKO",
          "pcs": 823,
          "kg": 250.3
        }
      ],
      "is_auto": true
    },
    {
      "col": "HV",
      "type": "MKO",
      "num": "100",
      "date": "2026-04-16",
      "revenue": 4742.27,
      "expense": 1925.17,
      "gross_profit": 2817.1,
      "margin_pct": 59.4,
      "weight_net": null,
      "weight_gross": null,
      "weight_vol": null,
      "marker1_tariff": 3.54,
      "marker2_volnet": 1.1931,
      "marker3_grossnet": 1.0019,
      "total_kg": 282.45,
      "total_pcs": 789,
      "mix": [
        {
          "country": "UZ",
          "subtype": "MKO",
          "pcs": 789,
          "kg": 282.45
        }
      ],
      "is_auto": true
    },
    {
      "col": "HW",
      "type": "MKO",
      "num": "101",
      "date": "2026-04-16",
      "revenue": 6066.61,
      "expense": 4406.54,
      "gross_profit": 1660.07,
      "margin_pct": 27.36,
      "weight_net": null,
      "weight_gross": null,
      "weight_vol": null,
      "marker1_tariff": 7.85,
      "marker2_volnet": 1.468,
      "marker3_grossnet": 0.9857,
      "total_kg": 237.4,
      "total_pcs": 969,
      "mix": [
        {
          "country": "UZ",
          "subtype": "MKO",
          "pcs": 969,
          "kg": 237.4
        }
      ],
      "is_auto": false
    },
    {
      "col": "HX",
      "type": "MKO",
      "num": "102",
      "date": "2026-04-15",
      "revenue": 4903.59,
      "expense": 2347.5,
      "gross_profit": 2556.09,
      "margin_pct": 52.13,
      "weight_net": null,
      "weight_gross": null,
      "weight_vol": null,
      "marker1_tariff": 4.37,
      "marker2_volnet": 1.2761,
      "marker3_grossnet": 1.0182,
      "total_kg": 294.65,
      "total_pcs": 801,
      "mix": [
        {
          "country": "UZ",
          "subtype": "MKO",
          "pcs": 801,
          "kg": 294.65
        }
      ],
      "is_auto": true
    },
    {
      "col": "HY",
      "type": "MKO",
      "num": "103",
      "date": "2026-04-17",
      "revenue": 4234.83,
      "expense": 1893.16,
      "gross_profit": 2341.68,
      "margin_pct": 55.3,
      "weight_net": null,
      "weight_gross": null,
      "weight_vol": null,
      "marker1_tariff": 4.25,
      "marker2_volnet": 1.249,
      "marker3_grossnet": 1.0168,
      "total_kg": 249.8,
      "total_pcs": 711,
      "mix": [
        {
          "country": "UZ",
          "subtype": "MKO",
          "pcs": 711,
          "kg": 249.8
        }
      ],
      "is_auto": true
    },
    {
      "col": "HZ",
      "type": "MKO",
      "num": "104",
      "date": "2026-04-17",
      "revenue": 4851.92,
      "expense": 2399.16,
      "gross_profit": 2452.76,
      "margin_pct": 50.55,
      "weight_net": null,
      "weight_gross": null,
      "weight_vol": null,
      "marker1_tariff": 4.37,
      "marker2_volnet": 1.1722,
      "marker3_grossnet": 1.0288,
      "total_kg": 296.45,
      "total_pcs": 854,
      "mix": [
        {
          "country": "UZ",
          "subtype": "MKO",
          "pcs": 854,
          "kg": 296.45
        }
      ],
      "is_auto": true
    },
    {
      "col": "IA",
      "type": "MKO",
      "num": "105",
      "date": "2026-04-18",
      "revenue": 4768.66,
      "expense": 2074.77,
      "gross_profit": 2693.89,
      "margin_pct": 56.49,
      "weight_net": null,
      "weight_gross": null,
      "weight_vol": null,
      "marker1_tariff": 3.54,
      "marker2_volnet": 1.2716,
      "marker3_grossnet": 1.0186,
      "total_kg": 304.35,
      "total_pcs": 748,
      "mix": [
        {
          "country": "UZ",
          "subtype": "MKO",
          "pcs": 748,
          "kg": 304.35
        }
      ],
      "is_auto": true
    },
    {
      "col": "IB",
      "type": "MKO",
      "num": "106",
      "date": "2026-04-19",
      "revenue": 4263.21,
      "expense": 2042.03,
      "gross_profit": 2221.19,
      "margin_pct": 52.1,
      "weight_net": null,
      "weight_gross": null,
      "weight_vol": null,
      "marker1_tariff": 4.54,
      "marker2_volnet": 1.135,
      "marker3_grossnet": 0.9987,
      "total_kg": 260.35,
      "total_pcs": 751,
      "mix": [
        {
          "country": "UZ",
          "subtype": "MKO",
          "pcs": 751,
          "kg": 260.35
        }
      ],
      "is_auto": true
    }
  ]
}